pysyslink_toolkit/BlockRenderInformation.py
pysyslink_toolkit/CoreBlockPlugin.py
pysyslink_toolkit/HighLevelBlock.py
pysyslink_toolkit/HighLevelSystem.py
pysyslink_toolkit/LowLevelBlockStructure.py
pysyslink_toolkit/Plugin.py
pysyslink_toolkit/TextFileManager.py
pysyslink_toolkit/__init__.py
pysyslink_toolkit/api.py
pysyslink_toolkit/compile_system.py
pysyslink_toolkit/load_plugins.py
pysyslink_toolkit/simulate_system.py
pysyslink_toolkit-0.2.0.dist-info/licenses/LICENSE
pysyslink_toolkit-0.2.0.dist-info/METADATA
pysyslink_toolkit-0.2.0.dist-info/WHEEL
pysyslink_toolkit-0.2.0.dist-info/top_level.txt
pysyslink_toolkit-0.2.0.dist-info/RECORD
