Metadata-Version: 2.4
Name: pysyslink_toolkit
Version: 0.2.0
Summary: Toolkit for PySysLink block-based dynamic system simulator
Author-email: Pello Usabiaga <pellousabiaga@gmail.com>
Requires-Python: >=3.8
License-File: LICENSE
Requires-Dist: PyYAML>6.0.1
Requires-Dist: pysyslink_base==0.1.0
Provides-Extra: test
Requires-Dist: pytest; extra == "test"
Dynamic: license-file
